{
  "data": [
    {
      "id": "GG-2025-01-01-0",
      "name": "New Year's Day",
      "date": "2025-01-01",
      "country": "",
      "countryCode": "GG",
      "type": "public",
      "global": true,
      "createdAt": "2025-07-29T04:48:15.540Z",
      "updatedAt": "2025-07-29T04:48:15.540Z"
    },
    {
      "id": "GG-2025-04-18-1",
      "name": "Good Friday",
      "date": "2025-04-18",
      "country": "",
      "countryCode": "GG",
      "type": "public",
      "global": true,
      "createdAt": "2025-07-29T04:48:15.540Z",
      "updatedAt": "2025-07-29T04:48:15.540Z"
    },
    {
      "id": "GG-2025-04-21-2",
      "name": "Easter Monday",
      "date": "2025-04-21",
      "country": "",
      "countryCode": "GG",
      "type": "public",
      "global": true,
      "createdAt": "2025-07-29T04:48:15.540Z",
      "updatedAt": "2025-07-29T04:48:15.540Z"
    },
    {
      "id": "GG-2025-05-01-3",
      "name": "Early May Bank Holiday",
      "date": "2025-05-01",
      "country": "",
      "countryCode": "GG",
      "type": "public",
      "global": true,
      "createdAt": "2025-07-29T04:48:15.540Z",
      "updatedAt": "2025-07-29T04:48:15.540Z"
    },
    {
      "id": "GG-2025-05-09-4",
      "name": "Liberation Day",
      "date": "2025-05-09",
      "country": "",
      "countryCode": "GG",
      "type": "public",
      "global": true,
      "createdAt": "2025-07-29T04:48:15.540Z",
      "updatedAt": "2025-07-29T04:48:15.540Z"
    },
    {
      "id": "GG-2025-05-26-5",
      "name": "Spring Bank Holiday",
      "date": "2025-05-26",
      "country": "",
      "countryCode": "GG",
      "type": "public",
      "global": true,
      "createdAt": "2025-07-29T04:48:15.540Z",
      "updatedAt": "2025-07-29T04:48:15.540Z"
    },
    {
      "id": "GG-2025-08-25-6",
      "name": "Summer Bank Holiday",
      "date": "2025-08-25",
      "country": "",
      "countryCode": "GG",
      "type": "public",
      "global": true,
      "createdAt": "2025-07-29T04:48:15.540Z",
      "updatedAt": "2025-07-29T04:48:15.540Z"
    },
    {
      "id": "GG-2025-12-25-7",
      "name": "Christmas Day",
      "date": "2025-12-25",
      "country": "",
      "countryCode": "GG",
      "type": "public",
      "global": true,
      "createdAt": "2025-07-29T04:48:15.540Z",
      "updatedAt": "2025-07-29T04:48:15.540Z"
    },
    {
      "id": "GG-2025-12-26-8",
      "name": "Boxing Day",
      "date": "2025-12-26",
      "country": "",
      "countryCode": "GG",
      "type": "public",
      "global": true,
      "createdAt": "2025-07-29T04:48:15.540Z",
      "updatedAt": "2025-07-29T04:48:15.540Z"
    }
  ],
  "timestamp": 1753764495540,
  "ttl": 86400000,
  "key": "holiday:GG:2025"
}